{
  "softmax": {
    "auroc": 0.6847059085599332,
    "tpr@osr": {
      "0.05": {
        "tpr": 0.24781377016873998,
        "threshold": 0.8700480461120605
      },
      "0.1": {
        "tpr": 0.36346840743933984,
        "threshold": 0.7420030832290649
      },
      "0.2": {
        "tpr": 0.5038797881512501,
        "threshold": 0.5016757249832153
      }
    },
    "tau20": 0.5016757249832153
  },
  "softmax lse entropy": {
    "logsumexp": {
      "auroc": 0.6312273114370629,
      "tpr@osr": {
        "0.05": {
          "tpr": 0.24522724473457322,
          "threshold": 1.9908415079116821
        },
        "0.1": {
          "tpr": 0.35028944451287103,
          "threshold": 1.3317561149597168
        },
        "0.2": {
          "tpr": 0.46532824239438353,
          "threshold": 0.6924575567245483
        }
      },
      "tau20": 0.6924575567245483
    },
    "entropy": {
      "auroc": 0.6222292916562254,
      "tpr@osr": {
        "0.05": {
          "tpr": 0.23562015026481092,
          "threshold": 0.615990400314331
        },
        "0.1": {
          "tpr": 0.34314570759945806,
          "threshold": 1.2957909107208252
        },
        "0.2": {
          "tpr": 0.46027835940386747,
          "threshold": 2.2493185997009277
        }
      },
      "tau20": 2.2493185997009277
    }
  },
  "softmax temperature": {
    "auroc": 0.6863972992585952,
    "tpr@osr": {
      "0.05": {
        "tpr": 0.19586120401337792,
        "threshold": 0.9997718930244446
      },
      "0.1": {
        "tpr": 0.3012123745819398,
        "threshold": 0.9993748068809509
      },
      "0.2": {
        "tpr": 0.4604933110367893,
        "threshold": 0.9962643980979919
      }
    },
    "tau20": 0.9962643980979919
  },
  "softmax temperature lse entropy": {
    "logsumexp": {
      "auroc": 0.657575752341013,
      "tpr@osr": {
        "0.05": {
          "tpr": 0.19418896321070234,
          "threshold": 8.36046028137207
        },
        "0.1": {
          "tpr": 0.2999581939799331,
          "threshold": 7.327511310577393
        },
        "0.2": {
          "tpr": 0.4508779264214047,
          "threshold": 5.496832847595215
        }
      },
      "tau20": 5.496832847595215
    },
    "entropy": {
      "auroc": 0.647111885147714,
      "tpr@osr": {
        "0.05": {
          "tpr": 0.1757943143812709,
          "threshold": 3.320874668588658e-07
        },
        "0.1": {
          "tpr": 0.28198160535117056,
          "threshold": 1.1981414900219534e-06
        },
        "0.2": {
          "tpr": 0.4391722408026756,
          "threshold": 1.4408879906113725e-05
        }
      },
      "tau20": 1.4408879906113725e-05
    }
  },
  "gmm": {
    "0": {
      "logsumexp": {
        "auroc": 0.4688156051911902,
        "tpr@osr": {
          "0.05": {
            "tpr": 0.06934351521123291,
            "threshold": 205.35684204101562
          },
          "0.1": {
            "tpr": 0.12267520630619534,
            "threshold": 191.18017578125
          },
          "0.2": {
            "tpr": 0.21542061830274664,
            "threshold": 174.84124755859375
          }
        },
        "tau20": 174.84124755859375
      },
      "entropy": {
        "auroc": 0.6296389069227768,
        "tpr@osr": {
          "0.05": {
            "tpr": 0.0,
            "threshold": -Infinity
          },
          "0.1": {
            "tpr": 0.0,
            "threshold": -Infinity
          },
          "0.2": {
            "tpr": 0.5070821529745042,
            "threshold": -0.0
          }
        },
        "tau20": -0.0
      }
    },
    "1": {
      "logsumexp": {
        "auroc": 0.47645390674634086,
        "tpr@osr": {
          "0.05": {
            "tpr": 0.07513240546865378,
            "threshold": 121.6644287109375
          },
          "0.1": {
            "tpr": 0.13142012563123537,
            "threshold": 108.15496826171875
          },
          "0.2": {
            "tpr": 0.2268752309397709,
            "threshold": 92.30661010742188
          }
        },
        "tau20": 92.30661010742188
      },
      "entropy": {
        "auroc": 0.6191860706428645,
        "tpr@osr": {
          "0.05": {
            "tpr": 0.0,
            "threshold": -Infinity
          },
          "0.1": {
            "tpr": 0.0,
            "threshold": -Infinity
          },
          "0.2": {
            "tpr": 0.4849119349673605,
            "threshold": -0.0
          }
        },
        "tau20": -0.0
      }
    },
    "2": {
      "logsumexp": {
        "auroc": 0.49757961656393535,
        "tpr@osr": {
          "0.05": {
            "tpr": 0.0825224781377017,
            "threshold": 117.28994750976562
          },
          "0.1": {
            "tpr": 0.14398324916861682,
            "threshold": 101.0552978515625
          },
          "0.2": {
            "tpr": 0.2559428501046927,
            "threshold": 82.27999877929688
          }
        },
        "tau20": 82.27999877929688
      },
      "entropy": {
        "auroc": 0.6046960805482136,
        "tpr@osr": {
          "0.05": {
            "tpr": 0.0,
            "threshold": -Infinity
          },
          "0.1": {
            "tpr": 0.0,
            "threshold": -Infinity
          },
          "0.2": {
            "tpr": 0.4888533070575194,
            "threshold": -0.0
          }
        },
        "tau20": -0.0
      }
    },
    "3": {
      "logsumexp": {
        "auroc": 0.5067645317929614,
        "tpr@osr": {
          "0.05": {
            "tpr": 0.07537874122428871,
            "threshold": 163.98245239257812
          },
          "0.1": {
            "tpr": 0.1380711910333785,
            "threshold": 146.13247680664062
          },
          "0.2": {
            "tpr": 0.25508067495997044,
            "threshold": 123.27828979492188
          }
        },
        "tau20": 123.27828979492188
      },
      "entropy": {
        "auroc": 0.5964647486875171,
        "tpr@osr": {
          "0.05": {
            "tpr": 0.0,
            "threshold": -Infinity
          },
          "0.1": {
            "tpr": 0.0,
            "threshold": -Infinity
          },
          "0.2": {
            "tpr": 0.5407069836186722,
            "threshold": -0.0
          }
        },
        "tau20": -0.0
      }
    },
    "4": {
      "logsumexp": {
        "auroc": 0.4904063563190093,
        "tpr@osr": {
          "0.05": {
            "tpr": 0.06318512132035965,
            "threshold": 280.63812255859375
          },
          "0.1": {
            "tpr": 0.10986574701317896,
            "threshold": 257.616455078125
          },
          "0.2": {
            "tpr": 0.2187461510038182,
            "threshold": 228.70986938476562
          }
        },
        "tau20": 228.70986938476562
      },
      "entropy": {
        "auroc": 0.5860420634582377,
        "tpr@osr": {
          "0.05": {
            "tpr": 0.0,
            "threshold": -Infinity
          },
          "0.1": {
            "tpr": 0.0,
            "threshold": -Infinity
          },
          "0.2": {
            "tpr": 0.0,
            "threshold": -Infinity
          }
        },
        "tau20": -Infinity
      }
    },
    "5": {
      "logsumexp": {
        "auroc": 0.526433957304716,
        "tpr@osr": {
          "0.05": {
            "tpr": 0.08264564601551916,
            "threshold": 428.7253723144531
          },
          "0.1": {
            "tpr": 0.1465697746027836,
            "threshold": 396.03326416015625
          },
          "0.2": {
            "tpr": 0.2894445128710432,
            "threshold": 358.1787109375
          }
        },
        "tau20": 358.1787109375
      },
      "entropy": {
        "auroc": 0.5753034718352551,
        "tpr@osr": {
          "0.05": {
            "tpr": 0.0,
            "threshold": -Infinity
          },
          "0.1": {
            "tpr": 0.0,
            "threshold": -Infinity
          },
          "0.2": {
            "tpr": 0.0,
            "threshold": -Infinity
          }
        },
        "tau20": -Infinity
      }
    }
  },
  "gmm temperature": {
    "0": {
      "logsumexp": {
        "auroc": 0.45759001792842074,
        "tpr@osr": {
          "0.05": {
            "tpr": 0.0644168000985343,
            "threshold": 9.26906967163086
          },
          "0.1": {
            "tpr": 0.11282177608079813,
            "threshold": 8.69844913482666
          },
          "0.2": {
            "tpr": 0.2003941372090159,
            "threshold": 8.039692878723145
          }
        },
        "tau20": 8.039692878723145
      },
      "entropy": {
        "auroc": 0.6515505486514437,
        "tpr@osr": {
          "0.05": {
            "tpr": 0.20298066264318265,
            "threshold": 7.536190969403833e-05
          },
          "0.1": {
            "tpr": 0.3101367163443774,
            "threshold": 0.0020863693207502365
          },
          "0.2": {
            "tpr": 0.44303485650942237,
            "threshold": 0.038947951048612595
          }
        },
        "tau20": 0.038947951048612595
      }
    },
    "1": {
      "logsumexp": {
        "auroc": 0.4668319159738705,
        "tpr@osr": {
          "0.05": {
            "tpr": 0.07340805517920926,
            "threshold": 6.193967342376709
          },
          "0.1": {
            "tpr": 0.12242887055056041,
            "threshold": 5.566065788269043
          },
          "0.2": {
            "tpr": 0.21246458923512748,
            "threshold": 4.849471092224121
          }
        },
        "tau20": 4.849471092224121
      },
      "entropy": {
        "auroc": 0.6380383484170229,
        "tpr@osr": {
          "0.05": {
            "tpr": 0.20741470624461142,
            "threshold": 7.742959496681578e-06
          },
          "0.1": {
            "tpr": 0.30853553393275035,
            "threshold": 0.0007379432208836079
          },
          "0.2": {
            "tpr": 0.42924005419386624,
            "threshold": 0.021942269057035446
          }
        },
        "tau20": 0.021942269057035446
      }
    },
    "2": {
      "logsumexp": {
        "auroc": 0.48947406846849234,
        "tpr@osr": {
          "0.05": {
            "tpr": 0.0789506096809952,
            "threshold": 5.5150251388549805
          },
          "0.1": {
            "tpr": 0.13622367286611653,
            "threshold": 4.795040130615234
          },
          "0.2": {
            "tpr": 0.245966252001478,
            "threshold": 3.975849151611328
          }
        },
        "tau20": 3.975849151611328
      },
      "entropy": {
        "auroc": 0.6274900043796608,
        "tpr@osr": {
          "0.05": {
            "tpr": 0.2106170710678655,
            "threshold": 8.577930543651746e-07
          },
          "0.1": {
            "tpr": 0.30779652666584556,
            "threshold": 0.00041010588756762445
          },
          "0.2": {
            "tpr": 0.4244365069589851,
            "threshold": 0.022940652444958687
          }
        },
        "tau20": 0.022940652444958687
      }
    },
    "3": {
      "logsumexp": {
        "auroc": 0.49916749015690953,
        "tpr@osr": {
          "0.05": {
            "tpr": 0.07303855154575686,
            "threshold": 6.561209678649902
          },
          "0.1": {
            "tpr": 0.13388348318758467,
            "threshold": 5.873096942901611
          },
          "0.2": {
            "tpr": 0.2449809089789383,
            "threshold": 5.011552810668945
          }
        },
        "tau20": 5.011552810668945
      },
      "entropy": {
        "auroc": 0.6268513869996613,
        "tpr@osr": {
          "0.05": {
            "tpr": 0.20113314447592068,
            "threshold": 9.963890335029646e-08
          },
          "0.1": {
            "tpr": 0.30816603029929795,
            "threshold": 0.000105323750176467
          },
          "0.2": {
            "tpr": 0.4206183027466437,
            "threshold": 0.013566581532359123
          }
        },
        "tau20": 0.013566581532359123
      }
    },
    "4": {
      "logsumexp": {
        "auroc": 0.48079023032041157,
        "tpr@osr": {
          "0.05": {
            "tpr": 0.06059859588619288,
            "threshold": 8.869549751281738
          },
          "0.1": {
            "tpr": 0.1040768567557581,
            "threshold": 8.168598175048828
          },
          "0.2": {
            "tpr": 0.20581352383298435,
            "threshold": 7.31732702255249
          }
        },
        "tau20": 7.31732702255249
      },
      "entropy": {
        "auroc": 0.6314401674707679,
        "tpr@osr": {
          "0.05": {
            "tpr": 0.21788397585909594,
            "threshold": 1.1002583732988569e-08
          },
          "0.1": {
            "tpr": 0.3210986574701318,
            "threshold": 4.093442112207413e-05
          },
          "0.2": {
            "tpr": 0.428377879049144,
            "threshold": 0.008073443546891212
          }
        },
        "tau20": 0.008073443546891212
      }
    },
    "5": {
      "logsumexp": {
        "auroc": 0.520124619844941,
        "tpr@osr": {
          "0.05": {
            "tpr": 0.08092129572607464,
            "threshold": 11.526219367980957
          },
          "0.1": {
            "tpr": 0.14065771646754527,
            "threshold": 10.661039352416992
          },
          "0.2": {
            "tpr": 0.2820544402019953,
            "threshold": 9.69953441619873
          }
        },
        "tau20": 9.69953441619873
      },
      "entropy": {
        "auroc": 0.6299446208005994,
        "tpr@osr": {
          "0.05": {
            "tpr": 0.21295726074639734,
            "threshold": 4.25538093651312e-09
          },
          "0.1": {
            "tpr": 0.3198669786919571,
            "threshold": 4.698570046457462e-05
          },
          "0.2": {
            "tpr": 0.42887055056041384,
            "threshold": 0.0102464584633708
          }
        },
        "tau20": 0.0102464584633708
      }
    }
  },
  "gmm per class": {
    "2": {
      "auroc": 0.6476907372212006,
      "tpr@osr": {
        "0.05": {
          "tpr": 0.22453504126123908,
          "threshold": 6.25635709905481e-10
        },
        "0.1": {
          "tpr": 0.3324301022293386,
          "threshold": 8.225719284382649e-06
        },
        "0.2": {
          "tpr": 0.44217268136470006,
          "threshold": 0.0023262514732778072
        }
      },
      "tau20": 0.0023262514732778072
    },
    "3": {
      "auroc": 0.6508543541751433,
      "tpr@osr": {
        "0.05": {
          "tpr": 0.21960832614854045,
          "threshold": 9.262528521958302e-10
        },
        "0.1": {
          "tpr": 0.32442419017120333,
          "threshold": 6.723791557305958e-06
        },
        "0.2": {
          "tpr": 0.4443897031654145,
          "threshold": 0.0017245608614757657
        }
      },
      "tau20": 0.0017245608614757657
    },
    "4": {
      "auroc": 0.6414586913446715,
      "tpr@osr": {
        "0.05": {
          "tpr": 0.20618302746643674,
          "threshold": 9.273355416894447e-10
        },
        "0.1": {
          "tpr": 0.30323931518659936,
          "threshold": 2.1848263713764027e-06
        },
        "0.2": {
          "tpr": 0.4241901712033502,
          "threshold": 0.0005911866901442409
        }
      },
      "tau20": 0.0005911866901442409
    }
  }
}