{
  "softmax": {
    "auroc": 0.9130571423653207,
    "tpr@osr": {
      "0.05": {
        "tpr": 0.773421926910299,
        "threshold": 0.834023118019104
      },
      "0.1": {
        "tpr": 0.8299003322259136,
        "threshold": 0.6971119046211243
      },
      "0.2": {
        "tpr": 0.8757475083056478,
        "threshold": 0.48960235714912415
      }
    },
    "tau20": 0.48960235714912415
  },
  "softmax lse entropy": {
    "logsumexp": {
      "auroc": 0.8892373977766419,
      "tpr@osr": {
        "0.05": {
          "tpr": 0.7760797342192691,
          "threshold": 1.6721909046173096
        },
        "0.1": {
          "tpr": 0.8186046511627907,
          "threshold": 1.1588259935379028
        },
        "0.2": {
          "tpr": 0.8471760797342193,
          "threshold": 0.6725165247917175
        }
      },
      "tau20": 0.6725165247917175
    },
    "entropy": {
      "auroc": 0.9088047853309482,
      "tpr@osr": {
        "0.05": {
          "tpr": 0.7980066445182724,
          "threshold": 1.257476806640625
        },
        "0.1": {
          "tpr": 0.837873754152824,
          "threshold": 2.029179334640503
        },
        "0.2": {
          "tpr": 0.8637873754152824,
          "threshold": 2.6769516468048096
        }
      },
      "tau20": 2.6769516468048096
    }
  },
  "softmax temperature": {
    "auroc": 0.8894048536359461,
    "tpr@osr": {
      "0.05": {
        "tpr": 0.48746312684365783,
        "threshold": 0.9997968077659607
      },
      "0.1": {
        "tpr": 0.6969026548672567,
        "threshold": 0.9993318915367126
      },
      "0.2": {
        "tpr": 0.8672566371681416,
        "threshold": 0.9927364587783813
      }
    },
    "tau20": 0.9927364587783813
  },
  "softmax temperature lse entropy": {
    "logsumexp": {
      "auroc": 0.8975122040358159,
      "tpr@osr": {
        "0.05": {
          "tpr": 0.6246312684365781,
          "threshold": 7.878931522369385
        },
        "0.1": {
          "tpr": 0.7728613569321534,
          "threshold": 6.536268711090088
        },
        "0.2": {
          "tpr": 0.8805309734513275,
          "threshold": 4.047344207763672
        }
      },
      "tau20": 4.047344207763672
    },
    "entropy": {
      "auroc": 0.9233658339206933,
      "tpr@osr": {
        "0.05": {
          "tpr": 0.7382005899705014,
          "threshold": 4.231675120536238e-06
        },
        "0.1": {
          "tpr": 0.8222713864306784,
          "threshold": 2.7114736440125853e-05
        },
        "0.2": {
          "tpr": 0.8960176991150443,
          "threshold": 0.0009329371387138963
        }
      },
      "tau20": 0.0009329371387138963
    }
  },
  "gmm": {
    "0": {
      "logsumexp": {
        "auroc": 0.7564927804753386,
        "tpr@osr": {
          "0.05": {
            "tpr": 0.27375415282392024,
            "threshold": 184.6458740234375
          },
          "0.1": {
            "tpr": 0.39867109634551495,
            "threshold": 165.61871337890625
          },
          "0.2": {
            "tpr": 0.5548172757475083,
            "threshold": 140.11181640625
          }
        },
        "tau20": 140.11181640625
      },
      "entropy": {
        "auroc": 0.8156307899948889,
        "tpr@osr": {
          "0.05": {
            "tpr": 0.0,
            "threshold": -Infinity
          },
          "0.1": {
            "tpr": 0.0,
            "threshold": -Infinity
          },
          "0.2": {
            "tpr": 0.8504983388704319,
            "threshold": -0.0
          }
        },
        "tau20": -0.0
      }
    },
    "1": {
      "logsumexp": {
        "auroc": 0.7630670201891133,
        "tpr@osr": {
          "0.05": {
            "tpr": 0.3415282392026578,
            "threshold": 98.84695434570312
          },
          "0.1": {
            "tpr": 0.4425249169435216,
            "threshold": 84.276611328125
          },
          "0.2": {
            "tpr": 0.5687707641196014,
            "threshold": 62.248626708984375
          }
        },
        "tau20": 62.248626708984375
      },
      "entropy": {
        "auroc": 0.8292378769486327,
        "tpr@osr": {
          "0.05": {
            "tpr": 0.0,
            "threshold": -Infinity
          },
          "0.1": {
            "tpr": 0.840531561461794,
            "threshold": -0.0
          },
          "0.2": {
            "tpr": 0.8411960132890366,
            "threshold": 1.4433374182545616e-43
          }
        },
        "tau20": 1.4433374182545616e-43
      }
    },
    "2": {
      "logsumexp": {
        "auroc": 0.7934796671351905,
        "tpr@osr": {
          "0.05": {
            "tpr": 0.3674418604651163,
            "threshold": 93.77743530273438
          },
          "0.1": {
            "tpr": 0.5049833887043189,
            "threshold": 74.09710693359375
          },
          "0.2": {
            "tpr": 0.6611295681063123,
            "threshold": 48.06085205078125
          }
        },
        "tau20": 48.06085205078125
      },
      "entropy": {
        "auroc": 0.8285866023511372,
        "tpr@osr": {
          "0.05": {
            "tpr": 0.0,
            "threshold": -Infinity
          },
          "0.1": {
            "tpr": 0.8445182724252491,
            "threshold": -0.0
          },
          "0.2": {
            "tpr": 0.8451827242524917,
            "threshold": 1.4433374182545616e-43
          }
        },
        "tau20": 1.4433374182545616e-43
      }
    },
    "3": {
      "logsumexp": {
        "auroc": 0.819984267186302,
        "tpr@osr": {
          "0.05": {
            "tpr": 0.40996677740863785,
            "threshold": 133.05206298828125
          },
          "0.1": {
            "tpr": 0.5428571428571428,
            "threshold": 112.07672119140625
          },
          "0.2": {
            "tpr": 0.7023255813953488,
            "threshold": 81.36752319335938
          }
        },
        "tau20": 81.36752319335938
      },
      "entropy": {
        "auroc": 0.7972182069384105,
        "tpr@osr": {
          "0.05": {
            "tpr": 0.0,
            "threshold": -Infinity
          },
          "0.1": {
            "tpr": 0.0,
            "threshold": -Infinity
          },
          "0.2": {
            "tpr": 0.8631229235880399,
            "threshold": -0.0
          }
        },
        "tau20": -0.0
      }
    },
    "4": {
      "logsumexp": {
        "auroc": 0.8044770636340404,
        "tpr@osr": {
          "0.05": {
            "tpr": 0.30564784053156147,
            "threshold": 243.6474609375
          },
          "0.1": {
            "tpr": 0.49235880398671095,
            "threshold": 215.93563842773438
          },
          "0.2": {
            "tpr": 0.6717607973421927,
            "threshold": 180.03736877441406
          }
        },
        "tau20": 180.03736877441406
      },
      "entropy": {
        "auroc": 0.7678174115129057,
        "tpr@osr": {
          "0.05": {
            "tpr": 0.0,
            "threshold": -Infinity
          },
          "0.1": {
            "tpr": 0.0,
            "threshold": -Infinity
          },
          "0.2": {
            "tpr": 0.8863787375415283,
            "threshold": -0.0
          }
        },
        "tau20": -0.0
      }
    },
    "5": {
      "logsumexp": {
        "auroc": 0.8626764950166114,
        "tpr@osr": {
          "0.05": {
            "tpr": 0.5694352159468439,
            "threshold": 365.29376220703125
          },
          "0.1": {
            "tpr": 0.6970099667774087,
            "threshold": 338.0345458984375
          },
          "0.2": {
            "tpr": 0.8006644518272426,
            "threshold": 293.1126708984375
          }
        },
        "tau20": 293.1126708984375
      },
      "entropy": {
        "auroc": 0.7557235097751086,
        "tpr@osr": {
          "0.05": {
            "tpr": 0.0,
            "threshold": -Infinity
          },
          "0.1": {
            "tpr": 0.0,
            "threshold": -Infinity
          },
          "0.2": {
            "tpr": 0.891029900332226,
            "threshold": -0.0
          }
        },
        "tau20": -0.0
      }
    }
  },
  "gmm temperature": {
    "0": {
      "logsumexp": {
        "auroc": 0.7417754120879121,
        "tpr@osr": {
          "0.05": {
            "tpr": 0.24916943521594684,
            "threshold": 8.730502128601074
          },
          "0.1": {
            "tpr": 0.3554817275747508,
            "threshold": 8.012371063232422
          },
          "0.2": {
            "tpr": 0.5242524916943522,
            "threshold": 6.819074630737305
          }
        },
        "tau20": 6.819074630737305
      },
      "entropy": {
        "auroc": 0.8871482078967545,
        "tpr@osr": {
          "0.05": {
            "tpr": 0.6697674418604651,
            "threshold": 0.0003120850888080895
          },
          "0.1": {
            "tpr": 0.7714285714285715,
            "threshold": 0.005158328451216221
          },
          "0.2": {
            "tpr": 0.8358803986710963,
            "threshold": 0.04899602010846138
          }
        },
        "tau20": 0.04899602010846138
      }
    },
    "1": {
      "logsumexp": {
        "auroc": 0.7501744984666496,
        "tpr@osr": {
          "0.05": {
            "tpr": 0.332890365448505,
            "threshold": 5.100196838378906
          },
          "0.1": {
            "tpr": 0.40930232558139534,
            "threshold": 4.468175411224365
          },
          "0.2": {
            "tpr": 0.546843853820598,
            "threshold": 3.3894846439361572
          }
        },
        "tau20": 3.3894846439361572
      },
      "entropy": {
        "auroc": 0.8940666528239203,
        "tpr@osr": {
          "0.05": {
            "tpr": 0.7461794019933555,
            "threshold": 0.00069694739067927
          },
          "0.1": {
            "tpr": 0.7926910299003322,
            "threshold": 0.006795909255743027
          },
          "0.2": {
            "tpr": 0.8425249169435216,
            "threshold": 0.05624888464808464
          }
        },
        "tau20": 0.05624888464808464
      }
    },
    "2": {
      "logsumexp": {
        "auroc": 0.7827422214413495,
        "tpr@osr": {
          "0.05": {
            "tpr": 0.34485049833887044,
            "threshold": 4.506850242614746
          },
          "0.1": {
            "tpr": 0.4790697674418605,
            "threshold": 3.579185962677002
          },
          "0.2": {
            "tpr": 0.6325581395348837,
            "threshold": 2.532761335372925
          }
        },
        "tau20": 2.532761335372925
      },
      "entropy": {
        "auroc": 0.8952410235113724,
        "tpr@osr": {
          "0.05": {
            "tpr": 0.7528239202657807,
            "threshold": 0.0003608602564781904
          },
          "0.1": {
            "tpr": 0.8019933554817276,
            "threshold": 0.01081768423318863
          },
          "0.2": {
            "tpr": 0.8465116279069768,
            "threshold": 0.08349937200546265
          }
        },
        "tau20": 0.08349937200546265
      }
    },
    "3": {
      "logsumexp": {
        "auroc": 0.8125930392282137,
        "tpr@osr": {
          "0.05": {
            "tpr": 0.3833887043189369,
            "threshold": 5.432351112365723
          },
          "0.1": {
            "tpr": 0.5335548172757475,
            "threshold": 4.5181145668029785
          },
          "0.2": {
            "tpr": 0.6903654485049834,
            "threshold": 3.3914906978607178
          }
        },
        "tau20": 3.3914906978607178
      },
      "entropy": {
        "auroc": 0.8950904836442627,
        "tpr@osr": {
          "0.05": {
            "tpr": 0.7574750830564784,
            "threshold": 9.147607488557696e-05
          },
          "0.1": {
            "tpr": 0.8033222591362126,
            "threshold": 0.0045369574800133705
          },
          "0.2": {
            "tpr": 0.8431893687707641,
            "threshold": 0.06088883429765701
          }
        },
        "tau20": 0.06088883429765701
      }
    },
    "4": {
      "logsumexp": {
        "auroc": 0.7917933810375671,
        "tpr@osr": {
          "0.05": {
            "tpr": 0.29700996677740865,
            "threshold": 7.703126430511475
          },
          "0.1": {
            "tpr": 0.47043189368770766,
            "threshold": 6.888696670532227
          },
          "0.2": {
            "tpr": 0.6365448504983389,
            "threshold": 5.941665172576904
          }
        },
        "tau20": 5.941665172576904
      },
      "entropy": {
        "auroc": 0.8924262873754153,
        "tpr@osr": {
          "0.05": {
            "tpr": 0.748172757475083,
            "threshold": 5.930686711508315e-06
          },
          "0.1": {
            "tpr": 0.8019933554817276,
            "threshold": 0.0009791854536160827
          },
          "0.2": {
            "tpr": 0.8431893687707641,
            "threshold": 0.030109435319900513
          }
        },
        "tau20": 0.030109435319900513
      }
    },
    "5": {
      "logsumexp": {
        "auroc": 0.8574295617173525,
        "tpr@osr": {
          "0.05": {
            "tpr": 0.5621262458471761,
            "threshold": 9.828843116760254
          },
          "0.1": {
            "tpr": 0.6870431893687707,
            "threshold": 9.121349334716797
          },
          "0.2": {
            "tpr": 0.7900332225913621,
            "threshold": 8.087615966796875
          }
        },
        "tau20": 8.087615966796875
      },
      "entropy": {
        "auroc": 0.8904061781242014,
        "tpr@osr": {
          "0.05": {
            "tpr": 0.7289036544850498,
            "threshold": 6.069857363399933e-07
          },
          "0.1": {
            "tpr": 0.7986710963455149,
            "threshold": 0.0007930630235932767
          },
          "0.2": {
            "tpr": 0.8372093023255814,
            "threshold": 0.026469580829143524
          }
        },
        "tau20": 0.026469580829143524
      }
    }
  },
  "gmm per class": {
    "2": {
      "auroc": 0.8844273096089956,
      "tpr@osr": {
        "0.05": {
          "tpr": 0.7255813953488373,
          "threshold": 1.5824899435301631e-07
        },
        "0.1": {
          "tpr": 0.7827242524916943,
          "threshold": 9.36424476094544e-05
        },
        "0.2": {
          "tpr": 0.8299003322259136,
          "threshold": 0.009859850630164146
        }
      },
      "tau20": 0.009859850630164146
    },
    "3": {
      "auroc": 0.8921615448504984,
      "tpr@osr": {
        "0.05": {
          "tpr": 0.7388704318936877,
          "threshold": 2.818558186845621e-08
        },
        "0.1": {
          "tpr": 0.7853820598006644,
          "threshold": 6.12978619756177e-05
        },
        "0.2": {
          "tpr": 0.8372093023255814,
          "threshold": 0.006294006481766701
        }
      },
      "tau20": 0.006294006481766701
    },
    "4": {
      "auroc": 0.8918888161257348,
      "tpr@osr": {
        "0.05": {
          "tpr": 0.7362126245847176,
          "threshold": 6.72720767980195e-09
        },
        "0.1": {
          "tpr": 0.7794019933554818,
          "threshold": 3.0742459784960374e-05
        },
        "0.2": {
          "tpr": 0.8305647840531561,
          "threshold": 0.0078120483085513115
        }
      },
      "tau20": 0.0078120483085513115
    }
  }
}